spacyHttp/__main__.py
spacy_http-0.1.1.dist-info/METADATA
spacy_http-0.1.1.dist-info/RECORD
spacy_http-0.1.1.dist-info/WHEEL
spacy_http-0.1.1.dist-info/top_level.txt
